test_guide_pytest_json-0.0.10.dist-info/licenses/LICENSE
tg_pytest_json/__init__.py
tg_pytest_json/plugin.py
tg_pytest_json/report.py
test_guide_pytest_json-0.0.10.dist-info/METADATA
test_guide_pytest_json-0.0.10.dist-info/WHEEL
test_guide_pytest_json-0.0.10.dist-info/entry_points.txt
test_guide_pytest_json-0.0.10.dist-info/top_level.txt
test_guide_pytest_json-0.0.10.dist-info/RECORD
