Metadata-Version: 2.4
Name: test_guide_pytest_json
Version: 0.0.10
Summary: A pytest plugin to generate JSON reports, with ATX support.
Author: Tim Copeland
License-Expression: MIT
Classifier: Programming Language :: Python :: 3
Classifier: Operating System :: OS Independent
Requires-Python: >=3.10
License-File: LICENSE
Requires-Dist: python-dotenv>=1.0.1
Dynamic: license-file
